{
    "site_info": {
        "name": "6401 South Blvd",
        "gauge": "USGS Archdale Dr",
        "location": {
            "lat": 35.109028,
            "lon": -80.85939
        }
    },
    "current_conditions": {
        "temperature_f": 89.6,
        "temperature_c": 32,
        "wind_speed_mph": 16.6,
        "wind_direction": "NNW",
        "humidity_percent": 56,
        "conditions": "Clear",
        "precipitation_24h": 0.0
    },
    "forecast_7day": [
        {
            "day": "Today",
            "date": "2026-07-08",
            "high": 80,
            "low": 64,
            "precipitation_prob": 54,
            "wind_speed": "2 mph",
            "wind_direction": "N",
            "short_forecast": "Mostly Sunny then Chance Showers And Thunderstorms",
            "detailed_forecast": "A chance of showers and thunderstorms after 1pm. Mostly sunny, with a high near 80. North wind around 2 mph. Chance of precipitation is 50%. New rainfall amounts between a tenth and quarter of an inch possible."
        },
        {
            "day": "Thursday",
            "date": "2026-07-09",
            "high": 80,
            "low": 64,
            "precipitation_prob": 56,
            "wind_speed": "5 mph",
            "wind_direction": "W",
            "short_forecast": "Mostly Sunny then Showers And Thunderstorms Likely",
            "detailed_forecast": "Showers and thunderstorms likely after 2pm. Mostly sunny, with a high near 80. West wind around 5 mph. Chance of precipitation is 60%. New rainfall amounts less than a tenth of an inch possible."
        },
        {
            "day": "Friday",
            "date": "2026-07-10",
            "high": 81,
            "low": 65,
            "precipitation_prob": 58,
            "wind_speed": "5 mph",
            "wind_direction": "W",
            "short_forecast": "Showers And Thunderstorms Likely",
            "detailed_forecast": "A slight chance of rain showers between 9am and 11am, then showers and thunderstorms likely. Mostly sunny, with a high near 81. West wind around 5 mph. Chance of precipitation is 60%."
        },
        {
            "day": "Saturday",
            "date": "2026-07-11",
            "high": 78,
            "low": 64,
            "precipitation_prob": 69,
            "wind_speed": "3 mph",
            "wind_direction": "WNW",
            "short_forecast": "Slight Chance Showers And Thunderstorms then Chance Showers And Thunderstorms",
            "detailed_forecast": "A slight chance of showers and thunderstorms between 7am and 8am, then a chance of showers and thunderstorms between 8am and 2pm, then showers and thunderstorms likely. Mostly cloudy, with a high near 78. Chance of precipitation is 70%."
        },
        {
            "day": "Sunday",
            "date": "2026-07-12",
            "high": 75,
            "low": 63,
            "precipitation_prob": 83,
            "wind_speed": "2 mph",
            "wind_direction": "NW",
            "short_forecast": "Showers And Thunderstorms",
            "detailed_forecast": "A slight chance of rain showers before 8am, then showers and thunderstorms. Mostly cloudy, with a high near 75. Chance of precipitation is 80%."
        },
        {
            "day": "Monday",
            "date": "2026-07-13",
            "high": 74,
            "low": 62,
            "precipitation_prob": 62,
            "wind_speed": "3 mph",
            "wind_direction": "NE",
            "short_forecast": "Showers And Thunderstorms Likely",
            "detailed_forecast": "A chance of rain showers before 8am, then showers and thunderstorms likely. Partly sunny, with a high near 74. Chance of precipitation is 60%."
        },
        {
            "day": "Tuesday",
            "date": "2026-07-14",
            "high": 78,
            "low": 63,
            "precipitation_prob": 20,
            "wind_speed": "0 to 5 mph",
            "wind_direction": "N",
            "short_forecast": "Mostly Sunny then Slight Chance Showers And Thunderstorms",
            "detailed_forecast": "A slight chance of showers and thunderstorms after 2pm. Mostly sunny, with a high near 78."
        }
    ],
    "active_alerts": [],
    "soil_moisture": {
        "level": "48%",
        "status": "Workable",
        "last_rain_inches": 0.0
    },
    "concrete_ops": {
        "pour_status": "CAUTION",
        "evap_rate_kg_m2_h": 1.195,
        "evap_status": "HIGH",
        "notes": [
            "High evaporation (1.195 kg/m\u00b2/h) - increase curing"
        ]
    },
    "activity_recommendations": {
        "concrete_pouring": {
            "status": "CAUTION",
            "notes": [
                "High evaporation (1.195 kg/m\u00b2/h) - increase curing"
            ]
        },
        "grading_excavation": {
            "status": "GO",
            "notes": [
                "Ground conditions suitable"
            ]
        },
        "asphalt_paving": {
            "status": "GO",
            "notes": []
        },
        "painting_coating": {
            "status": "GO",
            "notes": []
        },
        "crane_ops": {
            "status": "CAUTION",
            "notes": [
                "Monitor wind speeds closely"
            ]
        },
        "general_safety": []
    },
    "optimal_work_windows": {
        "concrete_pouring": [
            "Tuesday"
        ],
        "grading": [],
        "painting": []
    },
    "swppp_compliance": {
        "risk_level": "LOW",
        "map_labels": [
            {
                "lat": 35.108422,
                "lon": -80.85845,
                "label": "URGENT: Silt Fence Breach",
                "priority": "High",
                "color": [
                    230,
                    0,
                    0
                ]
            },
            {
                "lat": 35.10915,
                "lon": -80.85828,
                "label": "MAINTENANCE: Sediment Removal",
                "priority": "Med",
                "color": [
                    255,
                    165,
                    0
                ]
            },
            {
                "lat": 35.10962,
                "lon": -80.85985,
                "label": "STABILIZE: NW Slope Rills",
                "priority": "High",
                "color": [
                    230,
                    0,
                    0
                ]
            }
        ]
    },
    "last_updated": "2026-07-08T15:39:45.205487"
}