{
    "site_info": {
        "name": "6401 South Blvd",
        "gauge": "USGS Archdale Dr",
        "location": {
            "lat": 35.109028,
            "lon": -80.85939
        }
    },
    "current_conditions": {
        "temperature_f": 50.0,
        "temperature_c": 10,
        "wind_speed_mph": 16.6,
        "wind_direction": "ENE",
        "humidity_percent": 76,
        "conditions": "Light Rain",
        "precipitation_24h": 0.0
    },
    "forecast_7day": [
        {
            "day": "Today",
            "date": "2026-01-03",
            "high": 47,
            "low": 32,
            "precipitation_prob": 36,
            "wind_speed": "2 mph",
            "wind_direction": "ESE",
            "short_forecast": "Chance Light Rain then Partly Sunny",
            "detailed_forecast": "A chance of rain before 11am. Partly sunny, with a high near 47. East southeast wind around 2 mph. Chance of precipitation is 40%. New rainfall amounts less than a tenth of an inch possible."
        },
        {
            "day": "Sunday",
            "date": "2026-01-04",
            "high": 52,
            "low": 33,
            "precipitation_prob": 0,
            "wind_speed": "5 mph",
            "wind_direction": "NW",
            "short_forecast": "Areas Of Fog then Sunny",
            "detailed_forecast": "Areas of fog before 9am. Sunny, with a high near 52. Northwest wind around 5 mph."
        },
        {
            "day": "Monday",
            "date": "2026-01-05",
            "high": 55,
            "low": 38,
            "precipitation_prob": 0,
            "wind_speed": "6 mph",
            "wind_direction": "SSW",
            "short_forecast": "Mostly Sunny",
            "detailed_forecast": "Mostly sunny, with a high near 55. South southwest wind around 6 mph."
        },
        {
            "day": "Tuesday",
            "date": "2026-01-06",
            "high": 60,
            "low": 43,
            "precipitation_prob": 0,
            "wind_speed": "6 mph",
            "wind_direction": "SW",
            "short_forecast": "Mostly Sunny",
            "detailed_forecast": "Mostly sunny, with a high near 60."
        },
        {
            "day": "Wednesday",
            "date": "2026-01-07",
            "high": 62,
            "low": 44,
            "precipitation_prob": 5,
            "wind_speed": "5 mph",
            "wind_direction": "W",
            "short_forecast": "Partly Sunny",
            "detailed_forecast": "Partly sunny, with a high near 62."
        },
        {
            "day": "Thursday",
            "date": "2026-01-08",
            "high": 60,
            "low": 50,
            "precipitation_prob": 17,
            "wind_speed": "3 to 7 mph",
            "wind_direction": "S",
            "short_forecast": "Slight Chance Light Rain",
            "detailed_forecast": "A slight chance of rain after 9am. Mostly cloudy, with a high near 60."
        },
        {
            "day": "Friday",
            "date": "2026-01-09",
            "high": 62,
            "low": 48,
            "precipitation_prob": 31,
            "wind_speed": "7 mph",
            "wind_direction": "SSW",
            "short_forecast": "Chance Light Rain",
            "detailed_forecast": "A chance of rain. Mostly cloudy, with a high near 62. Chance of precipitation is 30%."
        }
    ],
    "active_alerts": [],
    "soil_moisture": {
        "level": "48%",
        "status": "Workable",
        "last_rain_inches": 0.0
    },
    "concrete_ops": {
        "pour_status": "GO",
        "evap_rate_kg_m2_h": 0.153,
        "evap_status": "LOW",
        "notes": [
            "Optimal conditions for concrete work"
        ]
    },
    "activity_recommendations": {
        "concrete_pouring": {
            "status": "GO",
            "notes": [
                "Optimal conditions for concrete work"
            ]
        },
        "grading_excavation": {
            "status": "GO",
            "notes": [
                "Ground conditions suitable"
            ]
        },
        "asphalt_paving": {
            "status": "GO",
            "notes": []
        },
        "painting_coating": {
            "status": "GO",
            "notes": []
        },
        "crane_ops": {
            "status": "CAUTION",
            "notes": [
                "Monitor wind speeds closely"
            ]
        },
        "general_safety": []
    },
    "optimal_work_windows": {
        "concrete_pouring": [
            "Sunday",
            "Monday",
            "Tuesday",
            "Wednesday",
            "Thursday"
        ],
        "grading": [
            "Sunday",
            "Monday",
            "Tuesday",
            "Wednesday",
            "Thursday"
        ],
        "painting": [
            "Sunday",
            "Monday",
            "Tuesday",
            "Wednesday",
            "Thursday"
        ]
    },
    "swppp_compliance": {
        "risk_level": "LOW",
        "map_labels": [
            {
                "lat": 35.108422,
                "lon": -80.85845,
                "label": "URGENT: Silt Fence Breach",
                "priority": "High",
                "color": [
                    230,
                    0,
                    0
                ]
            },
            {
                "lat": 35.10915,
                "lon": -80.85828,
                "label": "MAINTENANCE: Sediment Removal",
                "priority": "Med",
                "color": [
                    255,
                    165,
                    0
                ]
            },
            {
                "lat": 35.10962,
                "lon": -80.85985,
                "label": "STABILIZE: NW Slope Rills",
                "priority": "High",
                "color": [
                    230,
                    0,
                    0
                ]
            }
        ]
    },
    "last_updated": "2026-01-03T13:44:30.030356"
}